[
  {
    "model": "users.user",
    "pk": 1,
    "fields": {
      "password": "pbkdf2_sha256$600000$randomsalt$hashedpassword=",
      "last_login": null,
      "is_superuser": true,
      "is_staff": true,
      "is_active": true,
      "date_joined": "2025-12-23T10:00:00Z",
      "email": "admin@example.com",
      "first_name": "Админ",
      "last_name": "Главный",
      "avatar": null,
      "phone_number": "+79991234567",
      "country": "Russia",
      "telegram_chat_id": null
    }
  },
  {
    "model": "users.user",
    "pk": 2,
    "fields": {
      "password": "pbkdf2_sha256$600000$salt$hash=",
      "last_login": null,
      "is_superuser": false,
      "is_staff": false,
      "is_active": true,
      "date_joined": "2025-12-23T10:05:00Z",
      "email": "user@example.com",
      "first_name": "Обычный",
      "last_name": "Пользователь",
      "avatar": null,
      "phone_number": "+79995554433",
      "country": "Russia",
      "telegram_chat_id": 494820666
    }
  },
  {
    "model": "habits.habit",
    "pk": 1,
    "fields": {
      "user": 2,
      "place": "Дома",
      "time": "07:00:00",
      "action": "Сделать зарядку",
      "is_pleasant": false,
      "related_habit": null,
      "reward": "Выпить кофе",
      "periodicity": 1,
      "execution_time": 120,
      "is_public": false,
      "last_sent": null
    }
  },
  {
    "model": "habits.habit",
    "pk": 2,
    "fields": {
      "user": 2,
      "place": "Парк",
      "time": "18:00:00",
      "action": "Пробежать 5 км",
      "is_pleasant": false,
      "related_habit": null,
      "reward": "Съесть мороженое",
      "periodicity": 2,
      "execution_time": 100,
      "is_public": true,
      "last_sent": "2025-12-22T10:00:00Z"
    }
  },
  {
    "model": "habits.habit",
    "pk": 3,
    "fields": {
      "user": 2,
      "place": "Кухня",
      "time": "08:00:00",
      "action": "Выпить стакан воды",
      "is_pleasant": true,
      "related_habit": null,
      "reward": null,
      "periodicity": 1,
      "execution_time": 30,
      "is_public": false,
      "last_sent": null
    }
  }
]